[{"id": 14901, "login": "2020-05-12T07:09:28.085135Z", "logout": "2020-05-12T08:17:55.243611Z", "comments": "", "user": "Marek F\u00f6rster", "visit_type": 1, "facility": 5, "training_program": "Default 1 kg", "results": [{"visit": 14901, "activity": "Optimal Rhomb Isometric Test", "start_time": "2020-05-12T07:44:55Z", "end_time": "2020-05-12T07:55:11Z", "user_comments": "", "settings": {"global_settings": {"performances": {"rehab_parameter": 1.96, "position_to_length_m": [{"mm": 270, "id": 1, "name": "1 - Vertical Handle"}, {"mm": 430, "id": 2, "name": "2 - Horizontal Handle"}]}}, "arm_adjustment": "M", "performances_defaults": {"right_optimal_rhomb": {"arm_position_m": "1", "number_of_measurements": "3"}, "left_optimal_rhomb": {"arm_position_m": "1", "number_of_measurements": "3"}}, "performances_sequence": ["right_optimal_rhomb", "left_optimal_rhomb"]}, "results": {"actuators": [{"position": 75.0, "channel": 0.0}], "performances": {"right_optimal_rhomb": {"measurements": [150000.0, 170000.0, 180000.0], "arm_length": 270.0}, "left_optimal_rhomb": {"measurements": [150000.0, 170000.0, 180000.0], "arm_length": 270.0}}}, "training_activity": 9866}], "training_saission": 1}, {"id": 14902, "login": "2020-05-12T07:29:58.170277Z", "logout": "2020-05-12T08:28:04.565165Z", "comments": "", "user": "Marek F\u00f6rster", "visit_type": 1, "facility": 5, "training_program": "Default 1 kg", "results": [{"visit": 14902, "activity": "Optimal Rhomb Isometric Test", "start_time": "2020-05-12T08:00:37Z", "end_time": "2020-05-12T08:01:29Z", "user_comments": "", "settings": {"global_settings": {"performances": {"rehab_parameter": 1.96, "position_to_length_m": [{"mm": 270, "id": 1, "name": "1 - Vertical Handle"}, {"mm": 430, "id": 2, "name": "2 - Horizontal Handle"}]}}, "actuators": [{"position": 75, "channel": 0}], "arm_adjustment": "M", "performances_defaults": {"right_optimal_rhomb": {"arm_position_m": "1", "number_of_measurements": "3"}, "left_optimal_rhomb": {"arm_position_m": "1", "number_of_measurements": "3"}}, "performances_sequence": ["right_optimal_rhomb", "left_optimal_rhomb"]}, "results": {"actuators": [{"position": 75.0, "channel": 0.0}], "performances": {"right_optimal_rhomb": {"measurements": [150000.0, 160000.0, 170000.0], "arm_length": 270.0}, "left_optimal_rhomb": {"measurements": [150000.0, 160000.0, 170000.0], "arm_length": 270.0}}}, "training_activity": 9866}], "training_saission": 2}, {"id": 14903, "login": "2020-05-12T07:48:54.340998Z", "logout": "2020-05-12T09:10:25.097503Z", "comments": "", "user": "Marek F\u00f6rster", "visit_type": 1, "facility": 5, "training_program": "Default 1 kg", "results": [{"visit": 14903, "activity": "Optimal Rhomb Isometric Test", "start_time": "2020-05-12T08:25:39Z", "end_time": "2020-05-12T08:26:03Z", "user_comments": "", "settings": {"global_settings": {"performances": {"rehab_parameter": 1.96, "position_to_length_m": [{"mm": 270, "id": 1, "name": "1 - Vertical Handle"}, {"mm": 430, "id": 2, "name": "2 - Horizontal Handle"}]}}, "actuators": [{"position": 75, "channel": 0}], "arm_adjustment": "M", "performances_defaults": {"right_optimal_rhomb": {"arm_position_m": "1", "number_of_measurements": "3"}, "left_optimal_rhomb": {"arm_position_m": "1", "number_of_measurements": "3"}}, "performances_sequence": ["right_optimal_rhomb", "left_optimal_rhomb"]}, "results": {"actuators": [{"position": 75.0, "channel": 0.0}], "performances": {"right_optimal_rhomb": {"measurements": [150000.0, 160000.0, 170000.0], "arm_length": 270.0}, "left_optimal_rhomb": {"measurements": [150000.0, 160000.0, 170000.0], "arm_length": 270.0}}}, "training_activity": 9866}], "training_saission": 3}, {"id": 14904, "login": "2020-05-12T07:46:21.129890Z", "logout": "2020-05-12T09:11:32.369633Z", "comments": "", "user": "Marek F\u00f6rster", "visit_type": 1, "facility": 5, "training_program": "Default 1 kg", "results": [{"visit": 14904, "activity": "Optimal Rhomb Isometric Test", "start_time": "2020-05-12T08:27:34Z", "end_time": "2020-05-12T08:28:00Z", "user_comments": "", "settings": {"global_settings": {"performances": {"rehab_parameter": 1.96, "position_to_length_m": [{"mm": 270, "id": 1, "name": "1 - Vertical Handle"}, {"mm": 430, "id": 2, "name": "2 - Horizontal Handle"}]}}, "actuators": [{"position": 75, "channel": 0}], "arm_adjustment": "M", "performances_defaults": {"right_optimal_rhomb": {"arm_position_m": "1", "number_of_measurements": "3"}, "left_optimal_rhomb": {"arm_position_m": "1", "number_of_measurements": "3"}}, "performances_sequence": ["right_optimal_rhomb", "left_optimal_rhomb"]}, "results": {"actuators": [{"position": 75.0, "channel": 0.0}], "performances": {"right_optimal_rhomb": {"measurements": [150000.0, 160000.0, 170000.0], "arm_length": 270.0}, "left_optimal_rhomb": {"measurements": [150000.0, 160000.0, 170000.0], "arm_length": 270.0}}}, "training_activity": 9866}], "training_saission": 4}, {"id": 14905, "login": "2020-05-12T07:58:47.333009Z", "logout": "2020-05-12T09:04:19.898362Z", "comments": "", "user": "Marek F\u00f6rster", "visit_type": 1, "facility": 5, "training_program": "Default 1 kg", "results": [{"visit": 14905, "activity": "Optimal Rhomb Isometric Test", "start_time": "2020-05-12T08:36:02Z", "end_time": "2020-05-12T08:36:25Z", "user_comments": "", "settings": {"global_settings": {"performances": {"rehab_parameter": 1.96, "position_to_length_m": [{"mm": 270, "id": 1, "name": "1 - Vertical Handle"}, {"mm": 430, "id": 2, "name": "2 - Horizontal Handle"}]}}, "actuators": [{"position": 75, "channel": 0}], "arm_adjustment": "M", "performances_defaults": {"right_optimal_rhomb": {"arm_position_m": "1", "number_of_measurements": "3"}, "left_optimal_rhomb": {"arm_position_m": "1", "number_of_measurements": "3"}}, "performances_sequence": ["right_optimal_rhomb", "left_optimal_rhomb"]}, "results": {"actuators": [{"position": 75.0, "channel": 0.0}], "performances": {"right_optimal_rhomb": {"measurements": [150000.0, 160000.0, 170000.0], "arm_length": 270.0}, "left_optimal_rhomb": {"measurements": [150000.0, 160000.0, 170000.0], "arm_length": 270.0}}}, "training_activity": 9866}], "training_saission": 5}, {"id": 14906, "login": "2020-05-12T08:11:29.086448Z", "logout": "2020-05-12T09:25:54.011569Z", "comments": "", "user": "Marek F\u00f6rster", "visit_type": 1, "facility": 5, "training_program": "Default 1 kg", "results": [{"visit": 14906, "activity": "Optimal Rhomb Isometric Test", "start_time": "2020-05-12T08:53:09Z", "end_time": "2020-05-12T08:53:32Z", "user_comments": "", "settings": {"global_settings": {"performances": {"rehab_parameter": 1.96, "position_to_length_m": [{"mm": 270, "id": 1, "name": "1 - Vertical Handle"}, {"mm": 430, "id": 2, "name": "2 - Horizontal Handle"}]}}, "actuators": [{"position": 75, "channel": 0}], "arm_adjustment": "M", "performances_defaults": {"right_optimal_rhomb": {"arm_position_m": "1", "number_of_measurements": "3"}, "left_optimal_rhomb": {"arm_position_m": "1", "number_of_measurements": "3"}}, "performances_sequence": ["right_optimal_rhomb", "left_optimal_rhomb"]}, "results": {"actuators": [{"position": 75.0, "channel": 0.0}], "performances": {"right_optimal_rhomb": {"measurements": [150000.0, 160000.0, 170000.0], "arm_length": 270.0}, "left_optimal_rhomb": {"measurements": [150000.0, 160000.0, 170000.0], "arm_length": 270.0}}}, "training_activity": 9866}], "training_saission": 6}, {"id": 14907, "login": "2020-05-12T08:28:13.569848Z", "logout": "2020-05-12T09:21:40.069381Z", "comments": "", "user": "Marek F\u00f6rster", "visit_type": 1, "facility": 5, "training_program": "Default 1 kg", "results": [{"visit": 14907, "activity": "Optimal Rhomb Isometric Test", "start_time": "2020-05-12T08:58:51Z", "end_time": "2020-05-12T08:59:02Z", "user_comments": "", "settings": {"global_settings": {"performances": {"rehab_parameter": 1.96, "position_to_length_m": [{"mm": 270, "id": 1, "name": "1 - Vertical Handle"}, {"mm": 430, "id": 2, "name": "2 - Horizontal Handle"}]}}, "actuators": [{"position": 75, "channel": 0}], "arm_adjustment": "M", "performances_defaults": {"right_optimal_rhomb": {"arm_position_m": "1", "number_of_measurements": "3"}, "left_optimal_rhomb": {"arm_position_m": "1", "number_of_measurements": "3"}}, "performances_sequence": ["right_optimal_rhomb"]}, "results": {"actuators": [{"position": 75.0, "channel": 0.0}], "performances": {"right_optimal_rhomb": {"measurements": [150000.0, 160000.0, 170000.0], "arm_length": 270.0}}}, "training_activity": 9866}], "training_saission": 7}, {"id": 14934, "login": "2020-05-12T09:35:44.465081Z", "logout": "2020-05-12T11:00:47.068019Z", "comments": "", "user": "Marek F\u00f6rster", "visit_type": 1, "facility": 5, "training_program": "Default 1 kg", "results": [{"visit": 14934, "activity": "Optimal Rhomb Isometric Test", "start_time": "2020-05-12T10:24:07Z", "end_time": "2020-05-12T10:24:16Z", "user_comments": "", "settings": {"global_settings": {"performances": {"rehab_parameter": 1.96, "position_to_length_m": [{"mm": 270, "id": 1, "name": "1 - Vertical Handle"}, {"mm": 430, "id": 2, "name": "2 - Horizontal Handle"}]}}, "actuators": [{"position": 75, "channel": 0}], "arm_adjustment": "M", "performances_defaults": {"right_optimal_rhomb": {"arm_position_m": "2", "number_of_measurements": "3"}, "left_optimal_rhomb": {"arm_position_m": "1", "number_of_measurements": "3"}}, "performances_sequence": ["right_optimal_rhomb"]}, "results": {"actuators": [{"position": 0.0, "channel": 0.0}], "performances": {"right_optimal_rhomb": {"measurements": [150000.0, 160000.0, 170000.0], "arm_length": 430.0}}}, "training_activity": 9866}], "training_saission": 8}, {"id": 14945, "login": "2020-05-12T10:18:41.093044Z", "logout": "2020-05-12T11:30:24.514429Z", "comments": "", "user": "Marek F\u00f6rster", "visit_type": 1, "facility": 5, "training_program": "Default 1 kg", "results": [{"visit": 14945, "activity": "Optimal Rhomb Isometric Test", "start_time": "2020-05-12T10:41:55Z", "end_time": "2020-05-12T10:42:04Z", "user_comments": "", "settings": {"global_settings": {"performances": {"rehab_parameter": 1.96, "position_to_length_m": [{"mm": 270, "id": 1, "name": "1 - Vertical Handle"}, {"mm": 430, "id": 2, "name": "2 - Horizontal Handle"}]}}, "actuators": [{"position": 0, "channel": 0}], "arm_adjustment": "M", "performances_defaults": {"right_optimal_rhomb": {"arm_position_m": "2", "number_of_measurements": "3"}, "left_optimal_rhomb": {"arm_position_m": "1", "number_of_measurements": "3"}}, "performances_sequence": ["right_optimal_rhomb"]}, "results": {"actuators": [{"position": 0.0, "channel": 0.0}], "performances": {"right_optimal_rhomb": {"measurements": [150000.0, 160000.0, 170000.0], "arm_length": 430.0}}}, "training_activity": 9866}], "training_saission": 9}, {"id": 14946, "login": "2020-05-12T10:08:05.225998Z", "logout": "2020-05-12T11:35:20.198610Z", "comments": "", "user": "Marek F\u00f6rster", "visit_type": 1, "facility": 5, "training_program": "Default 1 kg", "results": [{"visit": 14946, "activity": "Optimal Rhomb Isometric Test", "start_time": "2020-05-12T10:53:39Z", "end_time": "2020-05-12T10:54:53Z", "user_comments": "", "settings": {"global_settings": {"performances": {"rehab_parameter": 1.96, "position_to_length_m": [{"mm": 270, "id": 1, "name": "1 - Vertical Handle"}, {"mm": 430, "id": 2, "name": "2 - Horizontal Handle"}]}}, "actuators": [{"position": 0, "channel": 0}], "arm_adjustment": "M", "performances_defaults": {"right_optimal_rhomb": {"arm_position_m": "2", "number_of_measurements": "3"}, "left_optimal_rhomb": {"arm_position_m": "1", "number_of_measurements": "3"}}, "performances_sequence": ["right_optimal_rhomb"]}, "results": {"actuators": [{"position": 0.0, "channel": 0.0}], "performances": {"right_optimal_rhomb": {"measurements": [0.0, 0.0, 0.0], "arm_length": 430.0}}}, "training_activity": 9866}], "training_saission": 10}, {"id": 14947, "login": "2020-05-12T10:35:10.873167Z", "logout": "2020-05-12T11:28:56.370075Z", "comments": "", "user": "Marek F\u00f6rster", "visit_type": 1, "facility": 5, "training_program": "Default 1 kg", "results": [{"visit": 14947, "activity": "Optimal Rhomb Isometric Test", "start_time": "2020-05-12T10:55:31Z", "end_time": "2020-05-12T10:55:39Z", "user_comments": "", "settings": {"global_settings": {"performances": {"rehab_parameter": 1.96, "position_to_length_m": [{"mm": 270, "id": 1, "name": "1 - Vertical Handle"}, {"mm": 430, "id": 2, "name": "2 - Horizontal Handle"}]}}, "actuators": [{"position": 0, "channel": 0}], "arm_adjustment": "M", "performances_defaults": {"right_optimal_rhomb": {"arm_position_m": "2", "number_of_measurements": "3"}, "left_optimal_rhomb": {"arm_position_m": "1", "number_of_measurements": "3"}}, "performances_sequence": ["right_optimal_rhomb"]}, "results": {"actuators": [{"position": 0.0, "channel": 0.0}], "performances": {"right_optimal_rhomb": {"measurements": [60000.0, 70000.0, 0.0], "arm_length": 430.0}}}, "training_activity": 9866}], "training_saission": 11}, {"id": 14948, "login": "2020-05-12T10:27:36.261014Z", "logout": "2020-05-12T11:45:42.974838Z", "comments": "", "user": "Marek F\u00f6rster", "visit_type": 1, "facility": 5, "training_program": "Default 1 kg", "results": [{"visit": 14948, "activity": "Optimal Rhomb Isometric Test", "start_time": "2020-05-12T11:19:09Z", "end_time": "2020-05-12T11:19:13Z", "user_comments": "", "settings": {"global_settings": {"performances": {"rehab_parameter": 1.96, "position_to_length_m": [{"mm": 270, "id": 1, "name": "1 - Vertical Handle"}, {"mm": 430, "id": 2, "name": "2 - Horizontal Handle"}]}}, "actuators": [{"position": 0, "channel": 0}], "arm_adjustment": "M", "performances_defaults": {"right_optimal_rhomb": {"arm_position_m": "2", "number_of_measurements": "3"}, "left_optimal_rhomb": {"arm_position_m": "1", "number_of_measurements": "3"}}, "performances_sequence": ["right_optimal_rhomb"]}, "results": {"actuators": [{"position": 0.0, "channel": 0.0}], "performances": {"right_optimal_rhomb": {"measurements": [0.0, 0.0, 0.0], "arm_length": 430.0}}}, "training_activity": 9866}], "training_saission": 12}, {"id": 14949, "login": "2020-05-12T11:23:49.942167Z", "logout": "2020-05-12T11:49:55.329642Z", "comments": "", "user": "Marek F\u00f6rster", "visit_type": 1, "facility": 5, "training_program": "Default 1 kg", "results": [{"visit": 14949, "activity": "Optimal Rhomb Isometric Test", "start_time": "2020-05-12T11:45:16Z", "end_time": "2020-05-12T11:45:20Z", "user_comments": "", "settings": {"global_settings": {"performances": {"rehab_parameter": 1.96, "position_to_length_m": [{"mm": 270, "id": 1, "name": "1 - Vertical Handle"}, {"mm": 430, "id": 2, "name": "2 - Horizontal Handle"}]}}, "actuators": [{"position": 0, "channel": 0}], "arm_adjustment": "M", "performances_defaults": {"right_optimal_rhomb": {"arm_position_m": "2", "number_of_measurements": "3"}, "left_optimal_rhomb": {"arm_position_m": "1", "number_of_measurements": "3"}}, "performances_sequence": ["right_optimal_rhomb"]}, "results": {"actuators": [{"position": 0.0, "channel": 0.0}], "performances": {"right_optimal_rhomb": {"measurements": [0.0, 0.0, 0.0], "arm_length": 430.0}}}, "training_activity": 9866}], "training_saission": 13}, {"id": 14950, "login": "2020-05-12T11:21:04.777754Z", "logout": "2020-05-12T12:15:20.064591Z", "comments": "", "user": "Marek F\u00f6rster", "visit_type": 1, "facility": 5, "training_program": "Default 1 kg", "results": [{"visit": 14950, "activity": "Optimal Rhomb Isometric Test", "start_time": "2020-05-12T11:47:55Z", "end_time": "2020-05-12T11:47:59Z", "user_comments": "", "settings": {"global_settings": {"performances": {"rehab_parameter": 1.96, "position_to_length_m": [{"mm": 270, "id": 1, "name": "1 - Vertical Handle"}, {"mm": 430, "id": 2, "name": "2 - Horizontal Handle"}]}}, "actuators": [{"position": 0, "channel": 0}], "arm_adjustment": "M", "performances_defaults": {"right_optimal_rhomb": {"arm_position_m": "2", "number_of_measurements": "3"}, "left_optimal_rhomb": {"arm_position_m": "1", "number_of_measurements": "3"}}, "performances_sequence": ["right_optimal_rhomb"]}, "results": {"actuators": [{"position": 0.0, "channel": 0.0}], "performances": {"right_optimal_rhomb": {"measurements": [0.0, 0.0, 0.0], "arm_length": 430.0}}}, "training_activity": 9866}], "training_saission": 14}, {"id": 14955, "login": "2020-05-12T11:43:33.489384Z", "logout": "2020-05-12T12:32:46.860496Z", "comments": "", "user": "Marek F\u00f6rster", "visit_type": 1, "facility": 5, "training_program": "Default 1 kg", "results": [{"visit": 14955, "activity": "Optimal Rhomb Isometric Test", "start_time": "2020-05-12T12:06:57Z", "end_time": "2020-05-12T12:07:01Z", "user_comments": "", "settings": {"global_settings": {"performances": {"rehab_parameter": 1.96, "position_to_length_m": [{"mm": 270, "id": 1, "name": "1 - Vertical Handle"}, {"mm": 430, "id": 2, "name": "2 - Horizontal Handle"}]}}, "actuators": [{"position": 0, "channel": 0}], "arm_adjustment": "M", "performances_defaults": {"right_optimal_rhomb": {"arm_position_m": "2", "number_of_measurements": "3"}, "left_optimal_rhomb": {"arm_position_m": "1", "number_of_measurements": "3"}}, "performances_sequence": ["right_optimal_rhomb"]}, "results": {"actuators": [{"position": 0.0, "channel": 0.0}], "performances": {"right_optimal_rhomb": {"measurements": [0.0, 0.0, 0.0], "arm_length": 430.0}}}, "training_activity": 9866}], "training_saission": 15}, {"id": 15149, "login": "2020-05-16T19:27:01.499037Z", "logout": "2020-05-16T20:11:18.068316Z", "comments": "", "user": "Marek F\u00f6rster", "visit_type": 1, "facility": 5, "training_program": "Default 1 kg", "results": [{"visit": 15149, "activity": "Optimal Rhomb Isometric Test", "start_time": "2020-05-16T19:33:30Z", "end_time": "2020-05-16T19:33:39Z", "user_comments": "", "settings": {"global_settings": {"performances": {"rehab_parameter": 1.96, "position_to_length_m": [{"mm": 270, "id": 1, "name": "1 - Vertical Handle"}, {"mm": 430, "id": 2, "name": "2 - Horizontal Handle"}]}}, "actuators": [{"position": 0, "channel": 0}], "arm_adjustment": "M", "performances_defaults": {"right_optimal_rhomb": {"arm_position_m": "2", "number_of_measurements": "3"}, "left_optimal_rhomb": {"arm_position_m": "1", "number_of_measurements": "3"}}, "performances_sequence": ["right_optimal_rhomb"]}, "results": {"actuators": [{"position": 0.0, "channel": 0.0}], "performances": {"right_optimal_rhomb": {"measurements": [150000.0, 160000.0, 170000.0], "arm_length": 430.0}}}, "training_activity": 9866}], "training_saission": 16}, {"id": 15150, "login": "2020-05-16T19:14:22.166830Z", "logout": "2020-05-16T19:57:00.488573Z", "comments": "", "user": "Marek F\u00f6rster", "visit_type": 1, "facility": 5, "training_program": "Default 1 kg", "results": [{"visit": 15150, "activity": "Optimal Rhomb Isometric Test", "start_time": "2020-05-16T19:34:00Z", "end_time": "2020-05-16T19:34:08Z", "user_comments": "", "settings": {"global_settings": {"performances": {"rehab_parameter": 1.96, "position_to_length_m": [{"mm": 270, "id": 1, "name": "1 - Vertical Handle"}, {"mm": 430, "id": 2, "name": "2 - Horizontal Handle"}]}}, "actuators": [{"position": 0, "channel": 0}], "arm_adjustment": "M", "performances_defaults": {"right_optimal_rhomb": {"arm_position_m": "2", "number_of_measurements": "3"}, "left_optimal_rhomb": {"arm_position_m": "1", "number_of_measurements": "3"}}, "performances_sequence": ["right_optimal_rhomb"]}, "results": {"actuators": [{"position": 0.0, "channel": 0.0}], "performances": {"right_optimal_rhomb": {"measurements": [60000.0, 70000.0, 0.0], "arm_length": 430.0}}}, "training_activity": 9866}], "training_saission": 17}, {"id": 15151, "login": "2020-05-16T18:56:04.624130Z", "logout": "2020-05-16T19:49:07.660562Z", "comments": "", "user": "Marek F\u00f6rster", "visit_type": 1, "facility": 5, "training_program": "Default 1 kg", "results": [{"visit": 15151, "activity": "Optimal Rhomb Isometric Test", "start_time": "2020-05-16T19:34:55Z", "end_time": "2020-05-16T19:34:59Z", "user_comments": "", "settings": {"global_settings": {"performances": {"rehab_parameter": 1.96, "position_to_length_m": [{"mm": 270, "id": 1, "name": "1 - Vertical Handle"}, {"mm": 430, "id": 2, "name": "2 - Horizontal Handle"}]}}, "actuators": [{"position": 0, "channel": 0}], "arm_adjustment": "M", "performances_defaults": {"right_optimal_rhomb": {"arm_position_m": "2", "number_of_measurements": "3"}, "left_optimal_rhomb": {"arm_position_m": "1", "number_of_measurements": "3"}}, "performances_sequence": ["right_optimal_rhomb"]}, "results": {"actuators": [{"position": 0.0, "channel": 0.0}], "performances": {"right_optimal_rhomb": {"measurements": [0.0, 0.0, 0.0], "arm_length": 430.0}}}, "training_activity": 9866}], "training_saission": 18}, {"id": 15181, "login": "2020-05-17T07:01:59.337296Z", "logout": "2020-05-17T07:41:31.663689Z", "comments": "", "user": "Marek F\u00f6rster", "visit_type": 1, "facility": 5, "training_program": "Default 1 kg", "results": [{"visit": 15181, "activity": "Optimal Rhomb Isometric Test", "start_time": "2020-05-17T07:27:30Z", "end_time": "2020-05-17T07:27:40Z", "user_comments": "", "settings": {"global_settings": {"performances": {"rehab_parameter": 1.96, "position_to_length_m": [{"mm": 270, "id": 1, "name": "1 - Vertical Handle"}, {"mm": 430, "id": 2, "name": "2 - Horizontal Handle"}]}}, "actuators": [{"position": 0, "channel": 0}], "arm_adjustment": "M", "performances_defaults": {"right_optimal_rhomb": {"arm_position_m": "2", "number_of_measurements": "3"}, "left_optimal_rhomb": {"arm_position_m": "1", "number_of_measurements": "3"}}, "performances_sequence": ["right_optimal_rhomb"]}, "results": {"actuators": [{"position": 0.0, "channel": 0.0}], "performances": {"right_optimal_rhomb": {"measurements": [150000.0, 160000.0, 170000.0], "arm_length": 430.0}}}, "training_activity": 9866}], "training_saission": 19}, {"id": 15182, "login": "2020-05-17T06:49:32.110556Z", "logout": "2020-05-17T08:07:23.740446Z", "comments": "", "user": "Marek F\u00f6rster", "visit_type": 1, "facility": 5, "training_program": "Default 1 kg", "results": [{"visit": 15182, "activity": "Optimal Rhomb Isometric Test", "start_time": "2020-05-17T07:28:01Z", "end_time": "2020-05-17T07:28:09Z", "user_comments": "", "settings": {"global_settings": {"performances": {"rehab_parameter": 1.96, "position_to_length_m": [{"mm": 270, "id": 1, "name": "1 - Vertical Handle"}, {"mm": 430, "id": 2, "name": "2 - Horizontal Handle"}]}}, "actuators": [{"position": 0, "channel": 0}], "arm_adjustment": "M", "performances_defaults": {"right_optimal_rhomb": {"arm_position_m": "2", "number_of_measurements": "3"}, "left_optimal_rhomb": {"arm_position_m": "1", "number_of_measurements": "3"}}, "performances_sequence": ["right_optimal_rhomb"]}, "results": {"actuators": [{"position": 0.0, "channel": 0.0}], "performances": {"right_optimal_rhomb": {"measurements": [60000.0, 70000.0, 0.0], "arm_length": 430.0}}}, "training_activity": 9866}], "training_saission": 20}, {"id": 15183, "login": "2020-05-17T07:25:45.110469Z", "logout": "2020-05-17T08:22:59.184276Z", "comments": "", "user": "Marek F\u00f6rster", "visit_type": 1, "facility": 5, "training_program": "Default 1 kg", "results": [{"visit": 15183, "activity": "Optimal Rhomb Isometric Test", "start_time": "2020-05-17T07:28:57Z", "end_time": "2020-05-17T07:29:01Z", "user_comments": "", "settings": {"global_settings": {"performances": {"rehab_parameter": 1.96, "position_to_length_m": [{"mm": 270, "id": 1, "name": "1 - Vertical Handle"}, {"mm": 430, "id": 2, "name": "2 - Horizontal Handle"}]}}, "actuators": [{"position": 0, "channel": 0}], "arm_adjustment": "M", "performances_defaults": {"right_optimal_rhomb": {"arm_position_m": "2", "number_of_measurements": "3"}, "left_optimal_rhomb": {"arm_position_m": "1", "number_of_measurements": "3"}}, "performances_sequence": ["right_optimal_rhomb"]}, "results": {"actuators": [{"position": 0.0, "channel": 0.0}], "performances": {"right_optimal_rhomb": {"measurements": [0.0, 0.0, 0.0], "arm_length": 430.0}}}, "training_activity": 9866}], "training_saission": 21}, {"id": 15238, "login": "2020-05-18T08:48:33.892213Z", "logout": "2020-05-18T10:02:06.205541Z", "comments": "", "user": "Marek F\u00f6rster", "visit_type": 1, "facility": 5, "training_program": "Default 1 kg", "results": [{"visit": 15238, "activity": "Optimal Rhomb Isometric Test", "start_time": "2020-05-18T09:23:11Z", "end_time": "2020-05-18T09:23:20Z", "user_comments": "", "settings": {"global_settings": {"performances": {"rehab_parameter": 1.96, "position_to_length_m": [{"mm": 270, "id": 1, "name": "1 - Vertical Handle"}, {"mm": 430, "id": 2, "name": "2 - Horizontal Handle"}]}}, "actuators": [{"position": 0, "channel": 0}], "arm_adjustment": "M", "performances_defaults": {"right_optimal_rhomb": {"arm_position_m": "2", "number_of_measurements": "3"}, "left_optimal_rhomb": {"arm_position_m": "1", "number_of_measurements": "3"}}, "performances_sequence": ["right_optimal_rhomb"]}, "results": {"actuators": [{"position": 0.0, "channel": 0.0}], "performances": {"right_optimal_rhomb": {"measurements": [150000.0, 160000.0, 170000.0], "arm_length": 430.0}}}, "training_activity": 9866}], "training_saission": 22}, {"id": 15239, "login": "2020-05-18T09:05:34.493302Z", "logout": "2020-05-18T09:47:09.720835Z", "comments": "", "user": "Marek F\u00f6rster", "visit_type": 1, "facility": 5, "training_program": "Default 1 kg", "results": [{"visit": 15239, "activity": "Optimal Rhomb Isometric Test", "start_time": "2020-05-18T09:23:42Z", "end_time": "2020-05-18T09:23:51Z", "user_comments": "", "settings": {"global_settings": {"performances": {"rehab_parameter": 1.96, "position_to_length_m": [{"mm": 270, "id": 1, "name": "1 - Vertical Handle"}, {"mm": 430, "id": 2, "name": "2 - Horizontal Handle"}]}}, "actuators": [{"position": 0, "channel": 0}], "arm_adjustment": "M", "performances_defaults": {"right_optimal_rhomb": {"arm_position_m": "2", "number_of_measurements": "3"}, "left_optimal_rhomb": {"arm_position_m": "1", "number_of_measurements": "3"}}, "performances_sequence": ["right_optimal_rhomb"]}, "results": {"actuators": [{"position": 0.0, "channel": 0.0}], "performances": {"right_optimal_rhomb": {"measurements": [60000.0, 70000.0, 0.0], "arm_length": 430.0}}}, "training_activity": 9866}], "training_saission": 23}, {"id": 15240, "login": "2020-05-18T08:52:54.794610Z", "logout": "2020-05-18T09:53:10.929695Z", "comments": "", "user": "Marek F\u00f6rster", "visit_type": 1, "facility": 5, "training_program": "Default 1 kg", "results": [{"visit": 15240, "activity": "Optimal Rhomb Isometric Test", "start_time": "2020-05-18T09:24:40Z", "end_time": "2020-05-18T09:24:44Z", "user_comments": "", "settings": {"global_settings": {"performances": {"rehab_parameter": 1.96, "position_to_length_m": [{"mm": 270, "id": 1, "name": "1 - Vertical Handle"}, {"mm": 430, "id": 2, "name": "2 - Horizontal Handle"}]}}, "actuators": [{"position": 0, "channel": 0}], "arm_adjustment": "M", "performances_defaults": {"right_optimal_rhomb": {"arm_position_m": "2", "number_of_measurements": "3"}, "left_optimal_rhomb": {"arm_position_m": "1", "number_of_measurements": "3"}}, "performances_sequence": ["right_optimal_rhomb"]}, "results": {"actuators": [{"position": 0.0, "channel": 0.0}], "performances": {"right_optimal_rhomb": {"measurements": [0.0, 0.0, 0.0], "arm_length": 430.0}}}, "training_activity": 9866}], "training_saission": 24}, {"id": 15291, "login": "2020-05-18T12:06:52.958292Z", "logout": "2020-05-18T12:44:18.372552Z", "comments": "", "user": "Marek F\u00f6rster", "visit_type": 1, "facility": 5, "training_program": "Default 1 kg", "results": [{"visit": 15291, "activity": "Optimal Rhomb Isometric Test", "start_time": "2020-05-18T12:24:30Z", "end_time": "2020-05-18T12:24:40Z", "user_comments": "", "settings": {"global_settings": {"performances": {"rehab_parameter": 1.96, "position_to_length_m": [{"mm": 270, "id": 1, "name": "1 - Vertical Handle"}, {"mm": 430, "id": 2, "name": "2 - Horizontal Handle"}]}}, "actuators": [{"position": 0, "channel": 0}], "arm_adjustment": "M", "performances_defaults": {"right_optimal_rhomb": {"arm_position_m": "2", "number_of_measurements": "3"}, "left_optimal_rhomb": {"arm_position_m": "1", "number_of_measurements": "3"}}, "performances_sequence": ["right_optimal_rhomb"]}, "results": {"actuators": [{"position": 0.0, "channel": 0.0}], "performances": {"right_optimal_rhomb": {"measurements": [150000.0, 160000.0, 170000.0], "arm_length": 430.0}}}, "training_activity": 9866}], "training_saission": 25}, {"id": 15292, "login": "2020-05-18T11:54:02.221395Z", "logout": "2020-05-18T12:49:36.516048Z", "comments": "", "user": "Marek F\u00f6rster", "visit_type": 1, "facility": 5, "training_program": "Default 1 kg", "results": [{"visit": 15292, "activity": "Optimal Rhomb Isometric Test", "start_time": "2020-05-18T12:25:00Z", "end_time": "2020-05-18T12:25:09Z", "user_comments": "", "settings": {"global_settings": {"performances": {"rehab_parameter": 1.96, "position_to_length_m": [{"mm": 270, "id": 1, "name": "1 - Vertical Handle"}, {"mm": 430, "id": 2, "name": "2 - Horizontal Handle"}]}}, "actuators": [{"position": 0, "channel": 0}], "arm_adjustment": "M", "performances_defaults": {"right_optimal_rhomb": {"arm_position_m": "2", "number_of_measurements": "3"}, "left_optimal_rhomb": {"arm_position_m": "1", "number_of_measurements": "3"}}, "performances_sequence": ["right_optimal_rhomb"]}, "results": {"actuators": [{"position": 0.0, "channel": 0.0}], "performances": {"right_optimal_rhomb": {"measurements": [60000.0, 70000.0, 0.0], "arm_length": 430.0}}}, "training_activity": 9866}], "training_saission": 26}, {"id": 15293, "login": "2020-05-18T11:48:04.088604Z", "logout": "2020-05-18T12:48:13.758330Z", "comments": "", "user": "Marek F\u00f6rster", "visit_type": 1, "facility": 5, "training_program": "Default 1 kg", "results": [{"visit": 15293, "activity": "Optimal Rhomb Isometric Test", "start_time": "2020-05-18T12:25:57Z", "end_time": "2020-05-18T12:26:00Z", "user_comments": "", "settings": {"global_settings": {"performances": {"rehab_parameter": 1.96, "position_to_length_m": [{"mm": 270, "id": 1, "name": "1 - Vertical Handle"}, {"mm": 430, "id": 2, "name": "2 - Horizontal Handle"}]}}, "actuators": [{"position": 0, "channel": 0}], "arm_adjustment": "M", "performances_defaults": {"right_optimal_rhomb": {"arm_position_m": "2", "number_of_measurements": "3"}, "left_optimal_rhomb": {"arm_position_m": "1", "number_of_measurements": "3"}}, "performances_sequence": ["right_optimal_rhomb"]}, "results": {"actuators": [{"position": 0.0, "channel": 0.0}], "performances": {"right_optimal_rhomb": {"measurements": [0.0, 0.0, 0.0], "arm_length": 430.0}}}, "training_activity": 9866}], "training_saission": 27}, {"id": 15342, "login": "2020-05-19T06:38:24.729944Z", "logout": "2020-05-19T07:50:07.744801Z", "comments": "", "user": "Marek F\u00f6rster", "visit_type": 1, "facility": 5, "training_program": "Default 1 kg", "results": [{"visit": 15342, "activity": "Optimal Rhomb Isometric Test", "start_time": "2020-05-19T07:08:23Z", "end_time": "2020-05-19T07:08:33Z", "user_comments": "", "settings": {"global_settings": {"performances": {"rehab_parameter": 1.96, "position_to_length_m": [{"mm": 270, "id": 1, "name": "1 - Vertical Handle"}, {"mm": 430, "id": 2, "name": "2 - Horizontal Handle"}]}}, "actuators": [{"position": 0, "channel": 0}], "arm_adjustment": "M", "performances_defaults": {"right_optimal_rhomb": {"arm_position_m": "2", "number_of_measurements": "3"}, "left_optimal_rhomb": {"arm_position_m": "1", "number_of_measurements": "3"}}, "performances_sequence": ["right_optimal_rhomb"]}, "results": {"actuators": [{"position": 0.0, "channel": 0.0}], "performances": {"right_optimal_rhomb": {"measurements": [150000.0, 160000.0, 170000.0], "arm_length": 430.0}}}, "training_activity": 9866}], "training_saission": 28}, {"id": 15343, "login": "2020-05-19T06:51:04.935771Z", "logout": "2020-05-19T07:54:47.900951Z", "comments": "", "user": "Marek F\u00f6rster", "visit_type": 1, "facility": 5, "training_program": "Default 1 kg", "results": [{"visit": 15343, "activity": "Optimal Rhomb Isometric Test", "start_time": "2020-05-19T07:08:55Z", "end_time": "2020-05-19T07:09:03Z", "user_comments": "", "settings": {"global_settings": {"performances": {"rehab_parameter": 1.96, "position_to_length_m": [{"mm": 270, "id": 1, "name": "1 - Vertical Handle"}, {"mm": 430, "id": 2, "name": "2 - Horizontal Handle"}]}}, "actuators": [{"position": 0, "channel": 0}], "arm_adjustment": "M", "performances_defaults": {"right_optimal_rhomb": {"arm_position_m": "2", "number_of_measurements": "3"}, "left_optimal_rhomb": {"arm_position_m": "1", "number_of_measurements": "3"}}, "performances_sequence": ["right_optimal_rhomb"]}, "results": {"actuators": [{"position": 0.0, "channel": 0.0}], "performances": {"right_optimal_rhomb": {"measurements": [60000.0, 70000.0, 0.0], "arm_length": 430.0}}}, "training_activity": 9866}], "training_saission": 29}, {"id": 15344, "login": "2020-05-19T06:53:02.867154Z", "logout": "2020-05-19T07:34:53.436012Z", "comments": "", "user": "Marek F\u00f6rster", "visit_type": 1, "facility": 5, "training_program": "Default 1 kg", "results": [{"visit": 15344, "activity": "Optimal Rhomb Isometric Test", "start_time": "2020-05-19T07:09:54Z", "end_time": "2020-05-19T07:09:58Z", "user_comments": "", "settings": {"global_settings": {"performances": {"rehab_parameter": 1.96, "position_to_length_m": [{"mm": 270, "id": 1, "name": "1 - Vertical Handle"}, {"mm": 430, "id": 2, "name": "2 - Horizontal Handle"}]}}, "actuators": [{"position": 0, "channel": 0}], "arm_adjustment": "M", "performances_defaults": {"right_optimal_rhomb": {"arm_position_m": "2", "number_of_measurements": "3"}, "left_optimal_rhomb": {"arm_position_m": "1", "number_of_measurements": "3"}}, "performances_sequence": ["right_optimal_rhomb"]}, "results": {"actuators": [{"position": 0.0, "channel": 0.0}], "performances": {"right_optimal_rhomb": {"measurements": [0.0, 0.0, 0.0], "arm_length": 430.0}}}, "training_activity": 9866}], "training_saission": 30}, {"id": 15402, "login": "2020-05-20T07:12:52.481816Z", "logout": "2020-05-20T08:03:56.806913Z", "comments": "", "user": "Marek F\u00f6rster", "visit_type": 1, "facility": 5, "training_program": "Default 1 kg", "results": [{"visit": 15402, "activity": "Optimal Rhomb Isometric Test", "start_time": "2020-05-20T07:48:24Z", "end_time": "2020-05-20T07:48:33Z", "user_comments": "", "settings": {"global_settings": {"performances": {"rehab_parameter": 1.96, "position_to_length_m": [{"mm": 270, "id": 1, "name": "1 - Vertical Handle"}, {"mm": 430, "id": 2, "name": "2 - Horizontal Handle"}]}}, "actuators": [{"position": 0, "channel": 0}], "arm_adjustment": "M", "performances_defaults": {"right_optimal_rhomb": {"arm_position_m": "2", "number_of_measurements": "3"}, "left_optimal_rhomb": {"arm_position_m": "1", "number_of_measurements": "3"}}, "performances_sequence": ["right_optimal_rhomb"]}, "results": {"actuators": [{"position": 0.0, "channel": 0.0}], "performances": {"right_optimal_rhomb": {"measurements": [150000.0, 160000.0, 170000.0], "arm_length": 430.0}}}, "training_activity": 9866}], "training_saission": 31}, {"id": 15403, "login": "2020-05-20T07:13:32.925609Z", "logout": "2020-05-20T08:30:45.445874Z", "comments": "", "user": "Marek F\u00f6rster", "visit_type": 1, "facility": 5, "training_program": "Default 1 kg", "results": [{"visit": 15403, "activity": "Optimal Rhomb Isometric Test", "start_time": "2020-05-20T07:48:55Z", "end_time": "2020-05-20T07:49:03Z", "user_comments": "", "settings": {"global_settings": {"performances": {"rehab_parameter": 1.96, "position_to_length_m": [{"mm": 270, "id": 1, "name": "1 - Vertical Handle"}, {"mm": 430, "id": 2, "name": "2 - Horizontal Handle"}]}}, "actuators": [{"position": 0, "channel": 0}], "arm_adjustment": "M", "performances_defaults": {"right_optimal_rhomb": {"arm_position_m": "2", "number_of_measurements": "3"}, "left_optimal_rhomb": {"arm_position_m": "1", "number_of_measurements": "3"}}, "performances_sequence": ["right_optimal_rhomb"]}, "results": {"actuators": [{"position": 0.0, "channel": 0.0}], "performances": {"right_optimal_rhomb": {"measurements": [60000.0, 70000.0, 0.0], "arm_length": 430.0}}}, "training_activity": 9866}], "training_saission": 32}, {"id": 15404, "login": "2020-05-20T07:16:52.517526Z", "logout": "2020-05-20T07:59:05.621733Z", "comments": "", "user": "Marek F\u00f6rster", "visit_type": 1, "facility": 5, "training_program": "Default 1 kg", "results": [{"visit": 15404, "activity": "Optimal Rhomb Isometric Test", "start_time": "2020-05-20T07:49:52Z", "end_time": "2020-05-20T07:49:56Z", "user_comments": "", "settings": {"global_settings": {"performances": {"rehab_parameter": 1.96, "position_to_length_m": [{"mm": 270, "id": 1, "name": "1 - Vertical Handle"}, {"mm": 430, "id": 2, "name": "2 - Horizontal Handle"}]}}, "actuators": [{"position": 0, "channel": 0}], "arm_adjustment": "M", "performances_defaults": {"right_optimal_rhomb": {"arm_position_m": "2", "number_of_measurements": "3"}, "left_optimal_rhomb": {"arm_position_m": "1", "number_of_measurements": "3"}}, "performances_sequence": ["right_optimal_rhomb"]}, "results": {"actuators": [{"position": 0.0, "channel": 0.0}], "performances": {"right_optimal_rhomb": {"measurements": [0.0, 0.0, 0.0], "arm_length": 430.0}}}, "training_activity": 9866}], "training_saission": 33}, {"id": 15450, "login": "2020-05-20T09:34:55.988029Z", "logout": "2020-05-20T10:48:04.334327Z", "comments": "", "user": "Marek F\u00f6rster", "visit_type": 1, "facility": 5, "training_program": "Default 1 kg", "results": [{"visit": 15450, "activity": "Optimal Rhomb Isometric Test", "start_time": "2020-05-20T10:08:16Z", "end_time": "2020-05-20T10:08:25Z", "user_comments": "", "settings": {"global_settings": {"performances": {"rehab_parameter": 1.96, "position_to_length_m": [{"mm": 270, "id": 1, "name": "1 - Vertical Handle"}, {"mm": 430, "id": 2, "name": "2 - Horizontal Handle"}]}}, "actuators": [{"position": 0, "channel": 0}], "arm_adjustment": "M", "performances_defaults": {"right_optimal_rhomb": {"arm_position_m": "2", "number_of_measurements": "3"}, "left_optimal_rhomb": {"arm_position_m": "1", "number_of_measurements": "3"}}, "performances_sequence": ["right_optimal_rhomb"]}, "results": {"actuators": [{"position": 0.0, "channel": 0.0}], "performances": {"right_optimal_rhomb": {"measurements": [150000.0, 160000.0, 170000.0], "arm_length": 430.0}}}, "training_activity": 9866}], "training_saission": 34}, {"id": 15451, "login": "2020-05-20T09:43:13.585807Z", "logout": "2020-05-20T10:46:02.636011Z", "comments": "", "user": "Marek F\u00f6rster", "visit_type": 1, "facility": 5, "training_program": "Default 1 kg", "results": [{"visit": 15451, "activity": "Optimal Rhomb Isometric Test", "start_time": "2020-05-20T10:08:46Z", "end_time": "2020-05-20T10:08:54Z", "user_comments": "", "settings": {"global_settings": {"performances": {"rehab_parameter": 1.96, "position_to_length_m": [{"mm": 270, "id": 1, "name": "1 - Vertical Handle"}, {"mm": 430, "id": 2, "name": "2 - Horizontal Handle"}]}}, "actuators": [{"position": 0, "channel": 0}], "arm_adjustment": "M", "performances_defaults": {"right_optimal_rhomb": {"arm_position_m": "2", "number_of_measurements": "3"}, "left_optimal_rhomb": {"arm_position_m": "1", "number_of_measurements": "3"}}, "performances_sequence": ["right_optimal_rhomb"]}, "results": {"actuators": [{"position": 0.0, "channel": 0.0}], "performances": {"right_optimal_rhomb": {"measurements": [60000.0, 70000.0, 0.0], "arm_length": 430.0}}}, "training_activity": 9866}], "training_saission": 35}, {"id": 15452, "login": "2020-05-20T09:34:42.082817Z", "logout": "2020-05-20T10:47:16.697314Z", "comments": "", "user": "Marek F\u00f6rster", "visit_type": 1, "facility": 5, "training_program": "Default 1 kg", "results": [{"visit": 15452, "activity": "Optimal Rhomb Isometric Test", "start_time": "2020-05-20T10:09:43Z", "end_time": "2020-05-20T10:09:47Z", "user_comments": "", "settings": {"global_settings": {"performances": {"rehab_parameter": 1.96, "position_to_length_m": [{"mm": 270, "id": 1, "name": "1 - Vertical Handle"}, {"mm": 430, "id": 2, "name": "2 - Horizontal Handle"}]}}, "actuators": [{"position": 0, "channel": 0}], "arm_adjustment": "M", "performances_defaults": {"right_optimal_rhomb": {"arm_position_m": "2", "number_of_measurements": "3"}, "left_optimal_rhomb": {"arm_position_m": "1", "number_of_measurements": "3"}}, "performances_sequence": ["right_optimal_rhomb"]}, "results": {"actuators": [{"position": 0.0, "channel": 0.0}], "performances": {"right_optimal_rhomb": {"measurements": [0.0, 0.0, 0.0], "arm_length": 430.0}}}, "training_activity": 9866}], "training_saission": 36}, {"id": 15490, "login": "2020-06-01T09:36:36.605415Z", "logout": "2020-06-01T10:45:10.186829Z", "comments": "", "user": "Marek F\u00f6rster", "visit_type": 1, "facility": 5, "training_program": "Default 1 kg", "results": [{"visit": 15490, "activity": "Optimal Rhomb Isometric Test", "start_time": "2020-06-01T09:57:25Z", "end_time": "2020-06-01T09:57:34Z", "user_comments": "", "settings": {"global_settings": {"performances": {"rehab_parameter": 1.96, "position_to_length_m": [{"mm": 270, "id": 1, "name": "1 - Vertical Handle"}, {"mm": 430, "id": 2, "name": "2 - Horizontal Handle"}]}}, "actuators": [{"position": 0, "channel": 0}], "arm_adjustment": "M", "performances_defaults": {"right_optimal_rhomb": {"arm_position_m": "2", "number_of_measurements": "3"}, "left_optimal_rhomb": {"arm_position_m": "1", "number_of_measurements": "3"}}, "performances_sequence": ["right_optimal_rhomb"]}, "results": {"actuators": [{"position": 0.0, "channel": 0.0}], "performances": {"right_optimal_rhomb": {"measurements": [150000.0, 160000.0, 170000.0], "arm_length": 430.0}}}, "training_activity": 9866}], "training_saission": 37}, {"id": 15491, "login": "2020-06-01T09:17:38.996221Z", "logout": "2020-06-01T10:21:18.906294Z", "comments": "", "user": "Marek F\u00f6rster", "visit_type": 1, "facility": 5, "training_program": "Default 1 kg", "results": [{"visit": 15491, "activity": "Optimal Rhomb Isometric Test", "start_time": "2020-06-01T09:57:57Z", "end_time": "2020-06-01T09:58:07Z", "user_comments": "", "settings": {"global_settings": {"performances": {"rehab_parameter": 1.96, "position_to_length_m": [{"mm": 270, "id": 1, "name": "1 - Vertical Handle"}, {"mm": 430, "id": 2, "name": "2 - Horizontal Handle"}]}}, "actuators": [{"position": 0, "channel": 0}], "arm_adjustment": "M", "performances_defaults": {"right_optimal_rhomb": {"arm_position_m": "2", "number_of_measurements": "3"}, "left_optimal_rhomb": {"arm_position_m": "1", "number_of_measurements": "3"}}, "performances_sequence": ["right_optimal_rhomb"]}, "results": {"actuators": [{"position": 0.0, "channel": 0.0}], "performances": {"right_optimal_rhomb": {"measurements": [60000.0, 70000.0, 0.0], "arm_length": 430.0}}}, "training_activity": 9866}], "training_saission": 38}, {"id": 15492, "login": "2020-06-01T09:48:34.426578Z", "logout": "2020-06-01T10:30:20.409223Z", "comments": "", "user": "Marek F\u00f6rster", "visit_type": 1, "facility": 5, "training_program": "Default 1 kg", "results": [{"visit": 15492, "activity": "Optimal Rhomb Isometric Test", "start_time": "2020-06-01T09:58:59Z", "end_time": "2020-06-01T09:59:03Z", "user_comments": "", "settings": {"global_settings": {"performances": {"rehab_parameter": 1.96, "position_to_length_m": [{"mm": 270, "id": 1, "name": "1 - Vertical Handle"}, {"mm": 430, "id": 2, "name": "2 - Horizontal Handle"}]}}, "actuators": [{"position": 0, "channel": 0}], "arm_adjustment": "M", "performances_defaults": {"right_optimal_rhomb": {"arm_position_m": "2", "number_of_measurements": "3"}, "left_optimal_rhomb": {"arm_position_m": "1", "number_of_measurements": "3"}}, "performances_sequence": ["right_optimal_rhomb"]}, "results": {"actuators": [{"position": 0.0, "channel": 0.0}], "performances": {"right_optimal_rhomb": {"measurements": [0.0, 0.0, 0.0], "arm_length": 430.0}}}, "training_activity": 9866}], "training_saission": 39}, {"id": 15540, "login": "2020-06-01T12:44:49.335207Z", "logout": "2020-06-01T14:08:19.565538Z", "comments": "", "user": "Marek F\u00f6rster", "visit_type": 1, "facility": 5, "training_program": "Default 1 kg", "results": [{"visit": 15540, "activity": "Optimal Rhomb Isometric Test", "start_time": "2020-06-01T13:21:09Z", "end_time": "2020-06-01T13:21:19Z", "user_comments": "", "settings": {"global_settings": {"performances": {"rehab_parameter": 1.96, "position_to_length_m": [{"mm": 270, "id": 1, "name": "1 - Vertical Handle"}, {"mm": 430, "id": 2, "name": "2 - Horizontal Handle"}]}}, "actuators": [{"position": 0, "channel": 0}], "arm_adjustment": "M", "performances_defaults": {"right_optimal_rhomb": {"arm_position_m": "2", "number_of_measurements": "3"}, "left_optimal_rhomb": {"arm_position_m": "1", "number_of_measurements": "3"}}, "performances_sequence": ["right_optimal_rhomb"]}, "results": {"actuators": [{"position": 0.0, "channel": 0.0}], "performances": {"right_optimal_rhomb": {"measurements": [150000.0, 160000.0, 170000.0], "arm_length": 430.0}}}, "training_activity": 9866}], "training_saission": 40}, {"id": 15541, "login": "2020-06-01T12:32:18.782374Z", "logout": "2020-06-01T13:45:47.400430Z", "comments": "", "user": "Marek F\u00f6rster", "visit_type": 1, "facility": 5, "training_program": "Default 1 kg", "results": [{"visit": 15541, "activity": "Optimal Rhomb Isometric Test", "start_time": "2020-06-01T13:21:41Z", "end_time": "2020-06-01T13:21:50Z", "user_comments": "", "settings": {"global_settings": {"performances": {"rehab_parameter": 1.96, "position_to_length_m": [{"mm": 270, "id": 1, "name": "1 - Vertical Handle"}, {"mm": 430, "id": 2, "name": "2 - Horizontal Handle"}]}}, "actuators": [{"position": 0, "channel": 0}], "arm_adjustment": "M", "performances_defaults": {"right_optimal_rhomb": {"arm_position_m": "2", "number_of_measurements": "3"}, "left_optimal_rhomb": {"arm_position_m": "1", "number_of_measurements": "3"}}, "performances_sequence": ["right_optimal_rhomb"]}, "results": {"actuators": [{"position": 0.0, "channel": 0.0}], "performances": {"right_optimal_rhomb": {"measurements": [60000.0, 70000.0, 0.0], "arm_length": 430.0}}}, "training_activity": 9866}], "training_saission": 41}, {"id": 15542, "login": "2020-06-01T12:54:09.054395Z", "logout": "2020-06-01T13:38:27.473573Z", "comments": "", "user": "Marek F\u00f6rster", "visit_type": 1, "facility": 5, "training_program": "Default 1 kg", "results": [{"visit": 15542, "activity": "Optimal Rhomb Isometric Test", "start_time": "2020-06-01T13:22:41Z", "end_time": "2020-06-01T13:22:44Z", "user_comments": "", "settings": {"global_settings": {"performances": {"rehab_parameter": 1.96, "position_to_length_m": [{"mm": 270, "id": 1, "name": "1 - Vertical Handle"}, {"mm": 430, "id": 2, "name": "2 - Horizontal Handle"}]}}, "actuators": [{"position": 0, "channel": 0}], "arm_adjustment": "M", "performances_defaults": {"right_optimal_rhomb": {"arm_position_m": "2", "number_of_measurements": "3"}, "left_optimal_rhomb": {"arm_position_m": "1", "number_of_measurements": "3"}}, "performances_sequence": ["right_optimal_rhomb"]}, "results": {"actuators": [{"position": 0.0, "channel": 0.0}], "performances": {"right_optimal_rhomb": {"measurements": [0.0, 0.0, 0.0], "arm_length": 430.0}}}, "training_activity": 9866}], "training_saission": 42}, {"id": 15590, "login": "2020-06-02T07:19:57.820605Z", "logout": "2020-06-02T08:07:26.434993Z", "comments": "", "user": "Marek F\u00f6rster", "visit_type": 1, "facility": 5, "training_program": "Default 1 kg", "results": [{"visit": 15590, "activity": "Optimal Rhomb Isometric Test", "start_time": "2020-06-02T07:57:12Z", "end_time": "2020-06-02T07:57:21Z", "user_comments": "", "settings": {"global_settings": {"performances": {"rehab_parameter": 1.96, "position_to_length_m": [{"mm": 270, "id": 1, "name": "1 - Vertical Handle"}, {"mm": 430, "id": 2, "name": "2 - Horizontal Handle"}]}}, "actuators": [{"position": 0, "channel": 0}], "arm_adjustment": "M", "performances_defaults": {"right_optimal_rhomb": {"arm_position_m": "2", "number_of_measurements": "3"}, "left_optimal_rhomb": {"arm_position_m": "1", "number_of_measurements": "3"}}, "performances_sequence": ["right_optimal_rhomb"]}, "results": {"actuators": [{"position": 0.0, "channel": 0.0}], "performances": {"right_optimal_rhomb": {"measurements": [150000.0, 160000.0, 170000.0], "arm_length": 430.0}}}, "training_activity": 9866}], "training_saission": 43}, {"id": 15591, "login": "2020-06-02T07:38:11.281123Z", "logout": "2020-06-02T08:10:29.684968Z", "comments": "", "user": "Marek F\u00f6rster", "visit_type": 1, "facility": 5, "training_program": "Default 1 kg", "results": [{"visit": 15591, "activity": "Optimal Rhomb Isometric Test", "start_time": "2020-06-02T07:57:43Z", "end_time": "2020-06-02T07:57:52Z", "user_comments": "", "settings": {"global_settings": {"performances": {"rehab_parameter": 1.96, "position_to_length_m": [{"mm": 270, "id": 1, "name": "1 - Vertical Handle"}, {"mm": 430, "id": 2, "name": "2 - Horizontal Handle"}]}}, "actuators": [{"position": 0, "channel": 0}], "arm_adjustment": "M", "performances_defaults": {"right_optimal_rhomb": {"arm_position_m": "2", "number_of_measurements": "3"}, "left_optimal_rhomb": {"arm_position_m": "1", "number_of_measurements": "3"}}, "performances_sequence": ["right_optimal_rhomb"]}, "results": {"actuators": [{"position": 0.0, "channel": 0.0}], "performances": {"right_optimal_rhomb": {"measurements": [60000.0, 70000.0, 0.0], "arm_length": 430.0}}}, "training_activity": 9866}], "training_saission": 44}, {"id": 15592, "login": "2020-06-02T07:41:51.098527Z", "logout": "2020-06-02T08:02:49.128958Z", "comments": "", "user": "Marek F\u00f6rster", "visit_type": 1, "facility": 5, "training_program": "Default 1 kg", "results": [{"visit": 15592, "activity": "Optimal Rhomb Isometric Test", "start_time": "2020-06-02T07:58:42Z", "end_time": "2020-06-02T07:58:45Z", "user_comments": "", "settings": {"global_settings": {"performances": {"rehab_parameter": 1.96, "position_to_length_m": [{"mm": 270, "id": 1, "name": "1 - Vertical Handle"}, {"mm": 430, "id": 2, "name": "2 - Horizontal Handle"}]}}, "actuators": [{"position": 0, "channel": 0}], "arm_adjustment": "M", "performances_defaults": {"right_optimal_rhomb": {"arm_position_m": "2", "number_of_measurements": "3"}, "left_optimal_rhomb": {"arm_position_m": "1", "number_of_measurements": "3"}}, "performances_sequence": ["right_optimal_rhomb"]}, "results": {"actuators": [{"position": 0.0, "channel": 0.0}], "performances": {"right_optimal_rhomb": {"measurements": [0.0, 0.0, 0.0], "arm_length": 430.0}}}, "training_activity": 9866}], "training_saission": 45}, {"id": 15639, "login": "2020-06-02T10:22:30.433738Z", "logout": "2020-06-02T11:03:33.744463Z", "comments": "", "user": "Marek F\u00f6rster", "visit_type": 1, "facility": 5, "training_program": "Default 1 kg", "results": [{"visit": 15639, "activity": "Optimal Rhomb Isometric Test", "start_time": "2020-06-02T10:48:10Z", "end_time": "2020-06-02T10:48:20Z", "user_comments": "", "settings": {"global_settings": {"performances": {"rehab_parameter": 1.96, "position_to_length_m": [{"mm": 270, "id": 1, "name": "1 - Vertical Handle"}, {"mm": 430, "id": 2, "name": "2 - Horizontal Handle"}]}}, "actuators": [{"position": 0, "channel": 0}], "arm_adjustment": "M", "performances_defaults": {"right_optimal_rhomb": {"arm_position_m": "2", "number_of_measurements": "3"}, "left_optimal_rhomb": {"arm_position_m": "1", "number_of_measurements": "3"}}, "performances_sequence": ["right_optimal_rhomb"]}, "results": {"actuators": [{"position": 0.0, "channel": 0.0}], "performances": {"right_optimal_rhomb": {"measurements": [150000.0, 160000.0, 170000.0], "arm_length": 430.0}}}, "training_activity": 9866}], "training_saission": 46}, {"id": 15640, "login": "2020-06-02T10:37:40.319664Z", "logout": "2020-06-02T11:12:58.851214Z", "comments": "", "user": "Marek F\u00f6rster", "visit_type": 1, "facility": 5, "training_program": "Default 1 kg", "results": [{"visit": 15640, "activity": "Optimal Rhomb Isometric Test", "start_time": "2020-06-02T10:48:40Z", "end_time": "2020-06-02T10:48:48Z", "user_comments": "", "settings": {"global_settings": {"performances": {"rehab_parameter": 1.96, "position_to_length_m": [{"mm": 270, "id": 1, "name": "1 - Vertical Handle"}, {"mm": 430, "id": 2, "name": "2 - Horizontal Handle"}]}}, "actuators": [{"position": 0, "channel": 0}], "arm_adjustment": "M", "performances_defaults": {"right_optimal_rhomb": {"arm_position_m": "2", "number_of_measurements": "3"}, "left_optimal_rhomb": {"arm_position_m": "1", "number_of_measurements": "3"}}, "performances_sequence": ["right_optimal_rhomb"]}, "results": {"actuators": [{"position": 0.0, "channel": 0.0}], "performances": {"right_optimal_rhomb": {"measurements": [60000.0, 70000.0, 0.0], "arm_length": 430.0}}}, "training_activity": 9866}], "training_saission": 47}, {"id": 15641, "login": "2020-06-02T10:06:43.310775Z", "logout": "2020-06-02T11:23:03.353614Z", "comments": "", "user": "Marek F\u00f6rster", "visit_type": 1, "facility": 5, "training_program": "Default 1 kg", "results": [{"visit": 15641, "activity": "Optimal Rhomb Isometric Test", "start_time": "2020-06-02T10:49:37Z", "end_time": "2020-06-02T10:49:41Z", "user_comments": "", "settings": {"global_settings": {"performances": {"rehab_parameter": 1.96, "position_to_length_m": [{"mm": 270, "id": 1, "name": "1 - Vertical Handle"}, {"mm": 430, "id": 2, "name": "2 - Horizontal Handle"}]}}, "actuators": [{"position": 0, "channel": 0}], "arm_adjustment": "M", "performances_defaults": {"right_optimal_rhomb": {"arm_position_m": "2", "number_of_measurements": "3"}, "left_optimal_rhomb": {"arm_position_m": "1", "number_of_measurements": "3"}}, "performances_sequence": ["right_optimal_rhomb"]}, "results": {"actuators": [{"position": 0.0, "channel": 0.0}], "performances": {"right_optimal_rhomb": {"measurements": [0.0, 0.0, 0.0], "arm_length": 430.0}}}, "training_activity": 9866}], "training_saission": 48}, {"id": 15691, "login": "2020-06-03T08:18:21.588890Z", "logout": "2020-06-03T08:53:34.322969Z", "comments": "", "user": "Marek F\u00f6rster", "visit_type": 1, "facility": 5, "training_program": "Default 1 kg", "results": [{"visit": 15691, "activity": "Optimal Rhomb Isometric Test", "start_time": "2020-06-03T08:38:08Z", "end_time": "2020-06-03T08:38:17Z", "user_comments": "", "settings": {"global_settings": {"performances": {"rehab_parameter": 1.96, "position_to_length_m": [{"mm": 270, "id": 1, "name": "1 - Vertical Handle"}, {"mm": 430, "id": 2, "name": "2 - Horizontal Handle"}]}}, "actuators": [{"position": 0, "channel": 0}], "arm_adjustment": "M", "performances_defaults": {"right_optimal_rhomb": {"arm_position_m": "2", "number_of_measurements": "3"}, "left_optimal_rhomb": {"arm_position_m": "1", "number_of_measurements": "3"}}, "performances_sequence": ["right_optimal_rhomb"]}, "results": {"actuators": [{"position": 0.0, "channel": 0.0}], "performances": {"right_optimal_rhomb": {"measurements": [150000.0, 160000.0, 170000.0], "arm_length": 430.0}}}, "training_activity": 9866}], "training_saission": 49}, {"id": 15692, "login": "2020-06-03T08:12:27.978582Z", "logout": "2020-06-03T09:07:16.679651Z", "comments": "", "user": "Marek F\u00f6rster", "visit_type": 1, "facility": 5, "training_program": "Default 1 kg", "results": [{"visit": 15692, "activity": "Optimal Rhomb Isometric Test", "start_time": "2020-06-03T08:38:39Z", "end_time": "2020-06-03T08:38:47Z", "user_comments": "", "settings": {"global_settings": {"performances": {"rehab_parameter": 1.96, "position_to_length_m": [{"mm": 270, "id": 1, "name": "1 - Vertical Handle"}, {"mm": 430, "id": 2, "name": "2 - Horizontal Handle"}]}}, "actuators": [{"position": 0, "channel": 0}], "arm_adjustment": "M", "performances_defaults": {"right_optimal_rhomb": {"arm_position_m": "2", "number_of_measurements": "3"}, "left_optimal_rhomb": {"arm_position_m": "1", "number_of_measurements": "3"}}, "performances_sequence": ["right_optimal_rhomb"]}, "results": {"actuators": [{"position": 0.0, "channel": 0.0}], "performances": {"right_optimal_rhomb": {"measurements": [60000.0, 70000.0, 0.0], "arm_length": 430.0}}}, "training_activity": 9866}], "training_saission": 50}, {"id": 15693, "login": "2020-06-03T08:06:47.828992Z", "logout": "2020-06-03T08:51:12.972239Z", "comments": "", "user": "Marek F\u00f6rster", "visit_type": 1, "facility": 5, "training_program": "Default 1 kg", "results": [{"visit": 15693, "activity": "Optimal Rhomb Isometric Test", "start_time": "2020-06-03T08:39:34Z", "end_time": "2020-06-03T08:39:38Z", "user_comments": "", "settings": {"global_settings": {"performances": {"rehab_parameter": 1.96, "position_to_length_m": [{"mm": 270, "id": 1, "name": "1 - Vertical Handle"}, {"mm": 430, "id": 2, "name": "2 - Horizontal Handle"}]}}, "actuators": [{"position": 0, "channel": 0}], "arm_adjustment": "M", "performances_defaults": {"right_optimal_rhomb": {"arm_position_m": "2", "number_of_measurements": "3"}, "left_optimal_rhomb": {"arm_position_m": "1", "number_of_measurements": "3"}}, "performances_sequence": ["right_optimal_rhomb"]}, "results": {"actuators": [{"position": 0.0, "channel": 0.0}], "performances": {"right_optimal_rhomb": {"measurements": [0.0, 0.0, 0.0], "arm_length": 430.0}}}, "training_activity": 9866}], "training_saission": 51}, {"id": 15742, "login": "2020-06-03T10:35:25.095086Z", "logout": "2020-06-03T11:56:06.340929Z", "comments": "", "user": "Marek F\u00f6rster", "visit_type": 1, "facility": 5, "training_program": "Default 1 kg", "results": [{"visit": 15742, "activity": "Optimal Rhomb Isometric Test", "start_time": "2020-06-03T11:16:22Z", "end_time": "2020-06-03T11:16:32Z", "user_comments": "", "settings": {"global_settings": {"performances": {"rehab_parameter": 1.96, "position_to_length_m": [{"mm": 270, "id": 1, "name": "1 - Vertical Handle"}, {"mm": 430, "id": 2, "name": "2 - Horizontal Handle"}]}}, "actuators": [{"position": 0, "channel": 0}], "arm_adjustment": "M", "performances_defaults": {"right_optimal_rhomb": {"arm_position_m": "2", "number_of_measurements": "3"}, "left_optimal_rhomb": {"arm_position_m": "1", "number_of_measurements": "3"}}, "performances_sequence": ["right_optimal_rhomb"]}, "results": {"actuators": [{"position": 0.0, "channel": 0.0}], "performances": {"right_optimal_rhomb": {"measurements": [150000.0, 160000.0, 170000.0], "arm_length": 430.0}}}, "training_activity": 9866}], "training_saission": 52}, {"id": 15743, "login": "2020-06-03T11:10:02.271849Z", "logout": "2020-06-03T11:57:32.025632Z", "comments": "", "user": "Marek F\u00f6rster", "visit_type": 1, "facility": 5, "training_program": "Default 1 kg", "results": [{"visit": 15743, "activity": "Optimal Rhomb Isometric Test", "start_time": "2020-06-03T11:16:54Z", "end_time": "2020-06-03T11:17:03Z", "user_comments": "", "settings": {"global_settings": {"performances": {"rehab_parameter": 1.96, "position_to_length_m": [{"mm": 270, "id": 1, "name": "1 - Vertical Handle"}, {"mm": 430, "id": 2, "name": "2 - Horizontal Handle"}]}}, "actuators": [{"position": 0, "channel": 0}], "arm_adjustment": "M", "performances_defaults": {"right_optimal_rhomb": {"arm_position_m": "2", "number_of_measurements": "3"}, "left_optimal_rhomb": {"arm_position_m": "1", "number_of_measurements": "3"}}, "performances_sequence": ["right_optimal_rhomb"]}, "results": {"actuators": [{"position": 0.0, "channel": 0.0}], "performances": {"right_optimal_rhomb": {"measurements": [60000.0, 70000.0, 0.0], "arm_length": 430.0}}}, "training_activity": 9866}], "training_saission": 53}, {"id": 15744, "login": "2020-06-03T10:36:07.023629Z", "logout": "2020-06-03T12:02:07.872683Z", "comments": "", "user": "Marek F\u00f6rster", "visit_type": 1, "facility": 5, "training_program": "Default 1 kg", "results": [{"visit": 15744, "activity": "Optimal Rhomb Isometric Test", "start_time": "2020-06-03T11:17:57Z", "end_time": "2020-06-03T11:18:02Z", "user_comments": "", "settings": {"global_settings": {"performances": {"rehab_parameter": 1.96, "position_to_length_m": [{"mm": 270, "id": 1, "name": "1 - Vertical Handle"}, {"mm": 430, "id": 2, "name": "2 - Horizontal Handle"}]}}, "actuators": [{"position": 0, "channel": 0}], "arm_adjustment": "M", "performances_defaults": {"right_optimal_rhomb": {"arm_position_m": "2", "number_of_measurements": "3"}, "left_optimal_rhomb": {"arm_position_m": "1", "number_of_measurements": "3"}}, "performances_sequence": ["right_optimal_rhomb"]}, "results": {"actuators": [{"position": 0.0, "channel": 0.0}], "performances": {"right_optimal_rhomb": {"measurements": [0.0, 0.0, 0.0], "arm_length": 430.0}}}, "training_activity": 9866}], "training_saission": 54}, {"id": 15791, "login": "2020-06-03T13:07:36.797271Z", "logout": "2020-06-03T13:57:07.694049Z", "comments": "", "user": "Marek F\u00f6rster", "visit_type": 1, "facility": 5, "training_program": "Default 1 kg", "results": [{"visit": 15791, "activity": "Optimal Rhomb Isometric Test", "start_time": "2020-06-03T13:25:50Z", "end_time": "2020-06-03T13:26:00Z", "user_comments": "", "settings": {"global_settings": {"performances": {"rehab_parameter": 1.96, "position_to_length_m": [{"mm": 270, "id": 1, "name": "1 - Vertical Handle"}, {"mm": 430, "id": 2, "name": "2 - Horizontal Handle"}]}}, "actuators": [{"position": 0, "channel": 0}], "arm_adjustment": "M", "performances_defaults": {"right_optimal_rhomb": {"arm_position_m": "2", "number_of_measurements": "3"}, "left_optimal_rhomb": {"arm_position_m": "1", "number_of_measurements": "3"}}, "performances_sequence": ["right_optimal_rhomb"]}, "results": {"actuators": [{"position": 0.0, "channel": 0.0}], "performances": {"right_optimal_rhomb": {"measurements": [150000.0, 160000.0, 170000.0], "arm_length": 430.0}}}, "training_activity": 9866}], "training_saission": 55}, {"id": 15792, "login": "2020-06-03T13:13:30.199301Z", "logout": "2020-06-03T14:05:33.780806Z", "comments": "", "user": "Marek F\u00f6rster", "visit_type": 1, "facility": 5, "training_program": "Default 1 kg", "results": [{"visit": 15792, "activity": "Optimal Rhomb Isometric Test", "start_time": "2020-06-03T13:26:21Z", "end_time": "2020-06-03T13:26:30Z", "user_comments": "", "settings": {"global_settings": {"performances": {"rehab_parameter": 1.96, "position_to_length_m": [{"mm": 270, "id": 1, "name": "1 - Vertical Handle"}, {"mm": 430, "id": 2, "name": "2 - Horizontal Handle"}]}}, "actuators": [{"position": 0, "channel": 0}], "arm_adjustment": "M", "performances_defaults": {"right_optimal_rhomb": {"arm_position_m": "2", "number_of_measurements": "3"}, "left_optimal_rhomb": {"arm_position_m": "1", "number_of_measurements": "3"}}, "performances_sequence": ["right_optimal_rhomb"]}, "results": {"actuators": [{"position": 0.0, "channel": 0.0}], "performances": {"right_optimal_rhomb": {"measurements": [60000.0, 70000.0, 0.0], "arm_length": 430.0}}}, "training_activity": 9866}], "training_saission": 56}, {"id": 15793, "login": "2020-06-03T12:54:06.960603Z", "logout": "2020-06-03T13:37:11.870060Z", "comments": "", "user": "Marek F\u00f6rster", "visit_type": 1, "facility": 5, "training_program": "Default 1 kg", "results": [{"visit": 15793, "activity": "Optimal Rhomb Isometric Test", "start_time": "2020-06-03T13:27:20Z", "end_time": "2020-06-03T13:27:24Z", "user_comments": "", "settings": {"global_settings": {"performances": {"rehab_parameter": 1.96, "position_to_length_m": [{"mm": 270, "id": 1, "name": "1 - Vertical Handle"}, {"mm": 430, "id": 2, "name": "2 - Horizontal Handle"}]}}, "actuators": [{"position": 0, "channel": 0}], "arm_adjustment": "M", "performances_defaults": {"right_optimal_rhomb": {"arm_position_m": "2", "number_of_measurements": "3"}, "left_optimal_rhomb": {"arm_position_m": "1", "number_of_measurements": "3"}}, "performances_sequence": ["right_optimal_rhomb"]}, "results": {"actuators": [{"position": 0.0, "channel": 0.0}], "performances": {"right_optimal_rhomb": {"measurements": [0.0, 0.0, 0.0], "arm_length": 430.0}}}, "training_activity": 9866}], "training_saission": 57}, {"id": 15833, "login": "2020-06-04T07:13:25.049220Z", "logout": "2020-06-04T08:10:04.894779Z", "comments": "", "user": "Marek F\u00f6rster", "visit_type": 1, "facility": 5, "training_program": "Default 1 kg", "results": [{"visit": 15833, "activity": "Optimal Rhomb Isometric Test", "start_time": "2020-06-04T07:50:41Z", "end_time": "2020-06-04T07:50:51Z", "user_comments": "", "settings": {"global_settings": {"performances": {"rehab_parameter": 1.96, "position_to_length_m": [{"mm": 270, "id": 1, "name": "1 - Vertical Handle"}, {"mm": 430, "id": 2, "name": "2 - Horizontal Handle"}]}}, "actuators": [{"position": 0, "channel": 0}], "arm_adjustment": "M", "performances_defaults": {"right_optimal_rhomb": {"arm_position_m": "2", "number_of_measurements": "3"}, "left_optimal_rhomb": {"arm_position_m": "1", "number_of_measurements": "3"}}, "performances_sequence": ["right_optimal_rhomb"]}, "results": {"actuators": [{"position": 0.0, "channel": 0.0}], "performances": {"right_optimal_rhomb": {"measurements": [150000.0, 160000.0, 170000.0], "arm_length": 430.0}}}, "training_activity": 9866}], "training_saission": 58}, {"id": 15834, "login": "2020-06-04T07:17:24.307612Z", "logout": "2020-06-04T08:11:14.269660Z", "comments": "", "user": "Marek F\u00f6rster", "visit_type": 1, "facility": 5, "training_program": "Default 1 kg", "results": [{"visit": 15834, "activity": "Optimal Rhomb Isometric Test", "start_time": "2020-06-04T07:51:12Z", "end_time": "2020-06-04T07:51:20Z", "user_comments": "", "settings": {"global_settings": {"performances": {"rehab_parameter": 1.96, "position_to_length_m": [{"mm": 270, "id": 1, "name": "1 - Vertical Handle"}, {"mm": 430, "id": 2, "name": "2 - Horizontal Handle"}]}}, "actuators": [{"position": 0, "channel": 0}], "arm_adjustment": "M", "performances_defaults": {"right_optimal_rhomb": {"arm_position_m": "2", "number_of_measurements": "3"}, "left_optimal_rhomb": {"arm_position_m": "1", "number_of_measurements": "3"}}, "performances_sequence": ["right_optimal_rhomb"]}, "results": {"actuators": [{"position": 0.0, "channel": 0.0}], "performances": {"right_optimal_rhomb": {"measurements": [60000.0, 70000.0, 0.0], "arm_length": 430.0}}}, "training_activity": 9866}], "training_saission": 59}, {"id": 15835, "login": "2020-06-04T07:44:20.124747Z", "logout": "2020-06-04T07:56:56.749292Z", "comments": "", "user": "Marek F\u00f6rster", "visit_type": 1, "facility": 5, "training_program": "Default 1 kg", "results": [{"visit": 15835, "activity": "Optimal Rhomb Isometric Test", "start_time": "2020-06-04T07:52:10Z", "end_time": "2020-06-04T07:52:14Z", "user_comments": "", "settings": {"global_settings": {"performances": {"rehab_parameter": 1.96, "position_to_length_m": [{"mm": 270, "id": 1, "name": "1 - Vertical Handle"}, {"mm": 430, "id": 2, "name": "2 - Horizontal Handle"}]}}, "actuators": [{"position": 0, "channel": 0}], "arm_adjustment": "M", "performances_defaults": {"right_optimal_rhomb": {"arm_position_m": "2", "number_of_measurements": "3"}, "left_optimal_rhomb": {"arm_position_m": "1", "number_of_measurements": "3"}}, "performances_sequence": ["right_optimal_rhomb"]}, "results": {"actuators": [{"position": 0.0, "channel": 0.0}], "performances": {"right_optimal_rhomb": {"measurements": [0.0, 0.0, 0.0], "arm_length": 430.0}}}, "training_activity": 9866}], "training_saission": 60}, {"id": 15850, "login": "2020-06-04T08:31:29.983761Z", "logout": "2020-06-04T09:45:30.244121Z", "comments": "", "user": "Marek F\u00f6rster", "visit_type": 1, "facility": 5, "training_program": "Default 1 kg", "results": [{"visit": 15850, "activity": "Optimal Rhomb Isometric Test", "start_time": "2020-06-04T09:10:12Z", "end_time": "2020-06-04T09:10:22Z", "user_comments": "", "settings": {"global_settings": {"performances": {"rehab_parameter": 1.96, "position_to_length_m": [{"mm": 270, "id": 1, "name": "1 - Vertical Handle"}, {"mm": 430, "id": 2, "name": "2 - Horizontal Handle"}]}}, "actuators": [{"position": 0, "channel": 0}], "arm_adjustment": "M", "performances_defaults": {"right_optimal_rhomb": {"arm_position_m": "2", "number_of_measurements": "3"}, "left_optimal_rhomb": {"arm_position_m": "1", "number_of_measurements": "3"}}, "performances_sequence": ["right_optimal_rhomb"]}, "results": {"actuators": [{"position": 0.0, "channel": 0.0}], "performances": {"right_optimal_rhomb": {"measurements": [150000.0, 160000.0, 170000.0], "arm_length": 430.0}}}, "training_activity": 9866}], "training_saission": 61}, {"id": 15851, "login": "2020-06-04T08:38:27.783361Z", "logout": "2020-06-04T09:32:41.108218Z", "comments": "", "user": "Marek F\u00f6rster", "visit_type": 1, "facility": 5, "training_program": "Default 1 kg", "results": [{"visit": 15851, "activity": "Optimal Rhomb Isometric Test", "start_time": "2020-06-04T09:10:42Z", "end_time": "2020-06-04T09:10:51Z", "user_comments": "", "settings": {"global_settings": {"performances": {"rehab_parameter": 1.96, "position_to_length_m": [{"mm": 270, "id": 1, "name": "1 - Vertical Handle"}, {"mm": 430, "id": 2, "name": "2 - Horizontal Handle"}]}}, "actuators": [{"position": 0, "channel": 0}], "arm_adjustment": "M", "performances_defaults": {"right_optimal_rhomb": {"arm_position_m": "2", "number_of_measurements": "3"}, "left_optimal_rhomb": {"arm_position_m": "1", "number_of_measurements": "3"}}, "performances_sequence": ["right_optimal_rhomb"]}, "results": {"actuators": [{"position": 0.0, "channel": 0.0}], "performances": {"right_optimal_rhomb": {"measurements": [60000.0, 70000.0, 0.0], "arm_length": 430.0}}}, "training_activity": 9866}], "training_saission": 62}, {"id": 15852, "login": "2020-06-04T08:40:36.942168Z", "logout": "2020-06-04T10:06:39.443903Z", "comments": "", "user": "Marek F\u00f6rster", "visit_type": 1, "facility": 5, "training_program": "Default 1 kg", "results": [{"visit": 15852, "activity": "Optimal Rhomb Isometric Test", "start_time": "2020-06-04T09:11:38Z", "end_time": "2020-06-04T09:11:43Z", "user_comments": "", "settings": {"global_settings": {"performances": {"rehab_parameter": 1.96, "position_to_length_m": [{"mm": 270, "id": 1, "name": "1 - Vertical Handle"}, {"mm": 430, "id": 2, "name": "2 - Horizontal Handle"}]}}, "actuators": [{"position": 0, "channel": 0}], "arm_adjustment": "M", "performances_defaults": {"right_optimal_rhomb": {"arm_position_m": "2", "number_of_measurements": "3"}, "left_optimal_rhomb": {"arm_position_m": "1", "number_of_measurements": "3"}}, "performances_sequence": ["right_optimal_rhomb"]}, "results": {"actuators": [{"position": 0.0, "channel": 0.0}], "performances": {"right_optimal_rhomb": {"measurements": [0.0, 0.0, 0.0], "arm_length": 430.0}}}, "training_activity": 9866}], "training_saission": 63}, {"id": 15900, "login": "2020-06-04T11:15:53.746126Z", "logout": "2020-06-04T12:07:17.202255Z", "comments": "", "user": "Marek F\u00f6rster", "visit_type": 1, "facility": 5, "training_program": "Default 1 kg", "results": [{"visit": 15900, "activity": "Optimal Rhomb Isometric Test", "start_time": "2020-06-04T11:46:15Z", "end_time": "2020-06-04T11:46:25Z", "user_comments": "", "settings": {"global_settings": {"performances": {"rehab_parameter": 1.96, "position_to_length_m": [{"mm": 270, "id": 1, "name": "1 - Vertical Handle"}, {"mm": 430, "id": 2, "name": "2 - Horizontal Handle"}]}}, "actuators": [{"position": 0, "channel": 0}], "arm_adjustment": "M", "performances_defaults": {"right_optimal_rhomb": {"arm_position_m": "2", "number_of_measurements": "3"}, "left_optimal_rhomb": {"arm_position_m": "1", "number_of_measurements": "3"}}, "performances_sequence": ["right_optimal_rhomb"]}, "results": {"actuators": [{"position": 0.0, "channel": 0.0}], "performances": {"right_optimal_rhomb": {"measurements": [150000.0, 160000.0, 170000.0], "arm_length": 430.0}}}, "training_activity": 9866}], "training_saission": 64}, {"id": 15901, "login": "2020-06-04T10:56:52.189891Z", "logout": "2020-06-04T12:30:51.804770Z", "comments": "", "user": "Marek F\u00f6rster", "visit_type": 1, "facility": 5, "training_program": "Default 1 kg", "results": [{"visit": 15901, "activity": "Optimal Rhomb Isometric Test", "start_time": "2020-06-04T11:46:46Z", "end_time": "2020-06-04T11:46:55Z", "user_comments": "", "settings": {"global_settings": {"performances": {"rehab_parameter": 1.96, "position_to_length_m": [{"mm": 270, "id": 1, "name": "1 - Vertical Handle"}, {"mm": 430, "id": 2, "name": "2 - Horizontal Handle"}]}}, "actuators": [{"position": 0, "channel": 0}], "arm_adjustment": "M", "performances_defaults": {"right_optimal_rhomb": {"arm_position_m": "2", "number_of_measurements": "3"}, "left_optimal_rhomb": {"arm_position_m": "1", "number_of_measurements": "3"}}, "performances_sequence": ["right_optimal_rhomb"]}, "results": {"actuators": [{"position": 0.0, "channel": 0.0}], "performances": {"right_optimal_rhomb": {"measurements": [60000.0, 70000.0, 0.0], "arm_length": 430.0}}}, "training_activity": 9866}], "training_saission": 65}, {"id": 15902, "login": "2020-06-04T11:10:45.050353Z", "logout": "2020-06-04T12:27:34.755898Z", "comments": "", "user": "Marek F\u00f6rster", "visit_type": 1, "facility": 5, "training_program": "Default 1 kg", "results": [{"visit": 15902, "activity": "Optimal Rhomb Isometric Test", "start_time": "2020-06-04T11:47:45Z", "end_time": "2020-06-04T11:47:49Z", "user_comments": "", "settings": {"global_settings": {"performances": {"rehab_parameter": 1.96, "position_to_length_m": [{"mm": 270, "id": 1, "name": "1 - Vertical Handle"}, {"mm": 430, "id": 2, "name": "2 - Horizontal Handle"}]}}, "actuators": [{"position": 0, "channel": 0}], "arm_adjustment": "M", "performances_defaults": {"right_optimal_rhomb": {"arm_position_m": "2", "number_of_measurements": "3"}, "left_optimal_rhomb": {"arm_position_m": "1", "number_of_measurements": "3"}}, "performances_sequence": ["right_optimal_rhomb"]}, "results": {"actuators": [{"position": 0.0, "channel": 0.0}], "performances": {"right_optimal_rhomb": {"measurements": [0.0, 0.0, 0.0], "arm_length": 430.0}}}, "training_activity": 9866}], "training_saission": 66}, {"id": 16037, "login": "2020-06-08T09:35:33.081890Z", "logout": "2020-06-08T11:16:16.470646Z", "comments": "", "user": "Marek F\u00f6rster", "visit_type": 1, "facility": 5, "training_program": "Default 1 kg", "results": [{"visit": 16037, "activity": "Optimal Rhomb Isometric Test", "start_time": "2020-06-08T10:21:05Z", "end_time": "2020-06-08T10:21:15Z", "user_comments": "", "settings": {"global_settings": {"performances": {"rehab_parameter": 1.96, "position_to_length_m": [{"mm": 270, "id": 1, "name": "1 - Vertical Handle"}, {"mm": 430, "id": 2, "name": "2 - Horizontal Handle"}]}}, "actuators": [{"position": 0, "channel": 0}], "arm_adjustment": "M", "performances_defaults": {"right_optimal_rhomb": {"arm_position_m": "2", "number_of_measurements": "3"}, "left_optimal_rhomb": {"arm_position_m": "1", "number_of_measurements": "3"}}, "performances_sequence": ["right_optimal_rhomb"]}, "results": {"actuators": [{"position": 0.0, "channel": 0.0}], "performances": {"right_optimal_rhomb": {"measurements": [150000.0, 160000.0, 170000.0], "arm_length": 430.0}}}, "training_activity": 9866}], "training_saission": 67}, {"id": 16038, "login": "2020-06-08T10:00:15.921998Z", "logout": "2020-06-08T10:40:51.145967Z", "comments": "", "user": "Marek F\u00f6rster", "visit_type": 1, "facility": 5, "training_program": "Default 1 kg", "results": [{"visit": 16038, "activity": "Optimal Rhomb Isometric Test", "start_time": "2020-06-08T10:21:36Z", "end_time": "2020-06-08T10:21:44Z", "user_comments": "", "settings": {"global_settings": {"performances": {"rehab_parameter": 1.96, "position_to_length_m": [{"mm": 270, "id": 1, "name": "1 - Vertical Handle"}, {"mm": 430, "id": 2, "name": "2 - Horizontal Handle"}]}}, "actuators": [{"position": 0, "channel": 0}], "arm_adjustment": "M", "performances_defaults": {"right_optimal_rhomb": {"arm_position_m": "2", "number_of_measurements": "3"}, "left_optimal_rhomb": {"arm_position_m": "1", "number_of_measurements": "3"}}, "performances_sequence": ["right_optimal_rhomb"]}, "results": {"actuators": [{"position": 0.0, "channel": 0.0}], "performances": {"right_optimal_rhomb": {"measurements": [60000.0, 70000.0, 0.0], "arm_length": 430.0}}}, "training_activity": 9866}], "training_saission": 68}, {"id": 16039, "login": "2020-06-08T10:05:05.948378Z", "logout": "2020-06-08T10:43:44.597877Z", "comments": "", "user": "Marek F\u00f6rster", "visit_type": 1, "facility": 5, "training_program": "Default 1 kg", "results": [{"visit": 16039, "activity": "Optimal Rhomb Isometric Test", "start_time": "2020-06-08T10:22:36Z", "end_time": "2020-06-08T10:22:40Z", "user_comments": "", "settings": {"global_settings": {"performances": {"rehab_parameter": 1.96, "position_to_length_m": [{"mm": 270, "id": 1, "name": "1 - Vertical Handle"}, {"mm": 430, "id": 2, "name": "2 - Horizontal Handle"}]}}, "actuators": [{"position": 0, "channel": 0}], "arm_adjustment": "M", "performances_defaults": {"right_optimal_rhomb": {"arm_position_m": "2", "number_of_measurements": "3"}, "left_optimal_rhomb": {"arm_position_m": "1", "number_of_measurements": "3"}}, "performances_sequence": ["right_optimal_rhomb"]}, "results": {"actuators": [{"position": 0.0, "channel": 0.0}], "performances": {"right_optimal_rhomb": {"measurements": [0.0, 0.0, 0.0], "arm_length": 430.0}}}, "training_activity": 9866}], "training_saission": 69}, {"id": 16511, "login": "2020-07-30T09:04:32.047674Z", "logout": "2020-07-30T10:10:12.248624Z", "comments": "", "user": "Marek F\u00f6rster", "visit_type": 1, "facility": 5, "training_program": "Default 1 kg", "results": [{"visit": 16511, "activity": "Optimal Rhomb Isometric Test", "start_time": "2020-07-30T09:43:58Z", "end_time": "2020-07-30T09:44:09Z", "user_comments": "", "settings": {"global_settings": {"performances": {"rehab_parameter": 1.96, "position_to_length_m": [{"mm": 270, "id": 1, "name": "1 - Vertical Handle"}, {"mm": 430, "id": 2, "name": "2 - Horizontal Handle"}]}}, "actuators": [{"position": 0, "channel": 0}], "arm_adjustment": "M", "performances_defaults": {"right_optimal_rhomb": {"arm_position_m": "2", "number_of_measurements": "3"}, "left_optimal_rhomb": {"arm_position_m": "1", "number_of_measurements": "3"}}, "performances_sequence": ["right_optimal_rhomb"]}, "results": {"actuators": [{"position": 0.0, "channel": 0.0}], "performances": {"right_optimal_rhomb": {"measurements": [150000.0, 160000.0, 170000.0], "arm_length": 430.0}}}, "training_activity": 9866}], "training_saission": 70}, {"id": 16512, "login": "2020-07-30T09:20:00.861312Z", "logout": "2020-07-30T10:19:26.237022Z", "comments": "", "user": "Marek F\u00f6rster", "visit_type": 1, "facility": 5, "training_program": "Default 1 kg", "results": [{"visit": 16512, "activity": "Optimal Rhomb Isometric Test", "start_time": "2020-07-30T09:44:32Z", "end_time": "2020-07-30T09:44:41Z", "user_comments": "", "settings": {"global_settings": {"performances": {"rehab_parameter": 1.96, "position_to_length_m": [{"mm": 270, "id": 1, "name": "1 - Vertical Handle"}, {"mm": 430, "id": 2, "name": "2 - Horizontal Handle"}]}}, "actuators": [{"position": 0, "channel": 0}], "arm_adjustment": "M", "performances_defaults": {"right_optimal_rhomb": {"arm_position_m": "2", "number_of_measurements": "3"}, "left_optimal_rhomb": {"arm_position_m": "1", "number_of_measurements": "3"}}, "performances_sequence": ["right_optimal_rhomb"]}, "results": {"actuators": [{"position": 0.0, "channel": 0.0}], "performances": {"right_optimal_rhomb": {"measurements": [60000.0, 70000.0, 0.0], "arm_length": 430.0}}}, "training_activity": 9866}], "training_saission": 71}, {"id": 16513, "login": "2020-07-30T09:26:18.986830Z", "logout": "2020-07-30T09:56:52.515821Z", "comments": "", "user": "Marek F\u00f6rster", "visit_type": 1, "facility": 5, "training_program": "Default 1 kg", "results": [{"visit": 16513, "activity": "Optimal Rhomb Isometric Test", "start_time": "2020-07-30T09:45:35Z", "end_time": "2020-07-30T09:45:39Z", "user_comments": "", "settings": {"global_settings": {"performances": {"rehab_parameter": 1.96, "position_to_length_m": [{"mm": 270, "id": 1, "name": "1 - Vertical Handle"}, {"mm": 430, "id": 2, "name": "2 - Horizontal Handle"}]}}, "actuators": [{"position": 0, "channel": 0}], "arm_adjustment": "M", "performances_defaults": {"right_optimal_rhomb": {"arm_position_m": "2", "number_of_measurements": "3"}, "left_optimal_rhomb": {"arm_position_m": "1", "number_of_measurements": "3"}}, "performances_sequence": ["right_optimal_rhomb"]}, "results": {"actuators": [{"position": 0.0, "channel": 0.0}], "performances": {"right_optimal_rhomb": {"measurements": [0.0, 0.0, 0.0], "arm_length": 430.0}}}, "training_activity": 9866}], "training_saission": 72}, {"id": 16531, "login": "2020-07-30T10:59:52.906430Z", "logout": "2020-07-30T12:20:30.895357Z", "comments": "", "user": "Marek F\u00f6rster", "visit_type": 1, "facility": 5, "training_program": "Default 1 kg", "results": [{"visit": 16531, "activity": "Optimal Rhomb Isometric Test", "start_time": "2020-07-30T11:55:37Z", "end_time": "2020-07-30T11:55:48Z", "user_comments": "", "settings": {"global_settings": {"performances": {"rehab_parameter": 1.96, "position_to_length_m": [{"mm": 270, "id": 1, "name": "1 - Vertical Handle"}, {"mm": 430, "id": 2, "name": "2 - Horizontal Handle"}]}}, "actuators": [{"position": 0, "channel": 0}], "arm_adjustment": "M", "performances_defaults": {"right_optimal_rhomb": {"arm_position_m": "2", "number_of_measurements": "3"}, "left_optimal_rhomb": {"arm_position_m": "1", "number_of_measurements": "3"}}, "performances_sequence": ["right_optimal_rhomb"]}, "results": {"actuators": [{"position": 0.0, "channel": 0.0}], "performances": {"right_optimal_rhomb": {"measurements": [150000.0, 160000.0, 170000.0], "arm_length": 430.0}}}, "training_activity": 9866}], "training_saission": 73}, {"id": 16560, "login": "2020-08-03T11:48:11.929190Z", "logout": "2020-08-03T13:22:08.777622Z", "comments": "", "user": "Marek F\u00f6rster", "visit_type": 1, "facility": 5, "training_program": "Default 1 kg", "results": [{"visit": 16560, "activity": "Optimal Rhomb Isometric Test", "start_time": "2020-08-03T12:28:28Z", "end_time": "2020-08-03T12:28:38Z", "user_comments": "", "settings": {"global_settings": {"performances": {"rehab_parameter": 1.96, "position_to_length_m": [{"mm": 270, "id": 1, "name": "1 - Vertical Handle"}, {"mm": 430, "id": 2, "name": "2 - Horizontal Handle"}]}}, "actuators": [{"position": 0, "channel": 0}], "arm_adjustment": "M", "performances_defaults": {"right_optimal_rhomb": {"arm_position_m": "2", "number_of_measurements": "3"}, "left_optimal_rhomb": {"arm_position_m": "1", "number_of_measurements": "3"}}, "performances_sequence": ["right_optimal_rhomb"]}, "results": {"actuators": [{"position": 0.0, "channel": 0.0}], "performances": {"right_optimal_rhomb": {"measurements": [150000.0, 160000.0, 170000.0], "arm_length": 430.0}}}, "training_activity": 9866}], "training_saission": 74}, {"id": 16561, "login": "2020-08-03T11:56:40.316430Z", "logout": "2020-08-03T12:54:06.083319Z", "comments": "", "user": "Marek F\u00f6rster", "visit_type": 1, "facility": 5, "training_program": "Default 1 kg", "results": [{"visit": 16561, "activity": "Optimal Rhomb Isometric Test", "start_time": "2020-08-03T12:29:02Z", "end_time": "2020-08-03T12:29:12Z", "user_comments": "", "settings": {"global_settings": {"performances": {"rehab_parameter": 1.96, "position_to_length_m": [{"mm": 270, "id": 1, "name": "1 - Vertical Handle"}, {"mm": 430, "id": 2, "name": "2 - Horizontal Handle"}]}}, "actuators": [{"position": 0, "channel": 0}], "arm_adjustment": "M", "performances_defaults": {"right_optimal_rhomb": {"arm_position_m": "2", "number_of_measurements": "3"}, "left_optimal_rhomb": {"arm_position_m": "1", "number_of_measurements": "3"}}, "performances_sequence": ["right_optimal_rhomb"]}, "results": {"actuators": [{"position": 0.0, "channel": 0.0}], "performances": {"right_optimal_rhomb": {"measurements": [60000.0, 70000.0, 0.0], "arm_length": 430.0}}}, "training_activity": 9866}], "training_saission": 75}, {"id": 16562, "login": "2020-08-03T11:59:20.982821Z", "logout": "2020-08-03T13:06:45.655148Z", "comments": "", "user": "Marek F\u00f6rster", "visit_type": 1, "facility": 5, "training_program": "Default 1 kg", "results": [{"visit": 16562, "activity": "Optimal Rhomb Isometric Test", "start_time": "2020-08-03T12:30:05Z", "end_time": "2020-08-03T12:30:10Z", "user_comments": "", "settings": {"global_settings": {"performances": {"rehab_parameter": 1.96, "position_to_length_m": [{"mm": 270, "id": 1, "name": "1 - Vertical Handle"}, {"mm": 430, "id": 2, "name": "2 - Horizontal Handle"}]}}, "actuators": [{"position": 0, "channel": 0}], "arm_adjustment": "M", "performances_defaults": {"right_optimal_rhomb": {"arm_position_m": "2", "number_of_measurements": "3"}, "left_optimal_rhomb": {"arm_position_m": "1", "number_of_measurements": "3"}}, "performances_sequence": ["right_optimal_rhomb"]}, "results": {"actuators": [{"position": 0.0, "channel": 0.0}], "performances": {"right_optimal_rhomb": {"measurements": [0.0, 0.0, 0.0], "arm_length": 430.0}}}, "training_activity": 9866}], "training_saission": 76}]